py3dinterpolations/__init__.py
py3dinterpolations/core/__init__.py
py3dinterpolations/core/grid3d.py
py3dinterpolations/core/griddata.py
py3dinterpolations/modelling/__init__.py
py3dinterpolations/modelling/estimator.py
py3dinterpolations/modelling/interpolate.py
py3dinterpolations/modelling/modeler.py
py3dinterpolations/modelling/preprocessor.py
py3dinterpolations/modelling/utils.py
py3dinterpolations/modelling/models/__init__.py
py3dinterpolations/modelling/models/deterministic.py
py3dinterpolations/modelling/models/idw.py
py3dinterpolations/plotting/__init__.py
py3dinterpolations/plotting/plotting.py
py3dinterpolations-0.4.4.dist-info/LICENSE
py3dinterpolations-0.4.4.dist-info/METADATA
py3dinterpolations-0.4.4.dist-info/WHEEL
py3dinterpolations-0.4.4.dist-info/top_level.txt
py3dinterpolations-0.4.4.dist-info/RECORD
