Metadata-Version: 2.1
Name: py3dinterpolations
Version: 0.4.4
Summary: quick 3D interpolation with python
Home-page: https://github.com/giocaizzi/py3dinterpolations
Author: giocaizzi
Author-email: giocaizzi@gmail.com
License: MIT
Project-URL: Documentation, https://giocaizzi.github.io/py3dinterpolations/
Project-URL: Bug Reports, https://github.com/giocaizzi/py3dinterpolations/issues
Project-URL: Source, https://github.com/giocaizzi/py3dinterpolations
Classifier: License :: OSI Approved :: MIT License
Classifier: Programming Language :: Python :: 3.7
Classifier: Programming Language :: Python :: 3.8
Classifier: Programming Language :: Python :: 3.9
Classifier: Programming Language :: Python :: 3.10
License-File: LICENSE
Requires-Dist: pandas
Requires-Dist: numpy
Requires-Dist: matplotlib
Requires-Dist: plotly
Requires-Dist: pykrige
Requires-Dist: scikit-learn
Provides-Extra: dev
Provides-Extra: docs
